agtools/__init__.py
agtools/cli.py
agtools/log_config.py
agtools/assemblers/__init__.py
agtools/assemblers/flye.py
agtools/assemblers/megahit.py
agtools/assemblers/myloasm.py
agtools/assemblers/spades.py
agtools/commands/__init__.py
agtools/commands/asqg2gfa.py
agtools/commands/clean.py
agtools/commands/component.py
agtools/commands/concat.py
agtools/commands/fastg2gfa.py
agtools/commands/filter.py
agtools/commands/gfa2adj.py
agtools/commands/gfa2dot.py
agtools/commands/gfa2fasta.py
agtools/commands/rename.py
agtools/commands/stats.py
agtools/core/__init__.py
agtools/core/contig_graph.py
agtools/core/fasta_parser.py
agtools/core/unitig_graph.py
agtools-1.0.2.dist-info/entry_points.txt
agtools-1.0.2.dist-info/licenses/LICENSE
agtools-1.0.2.dist-info/WHEEL
agtools-1.0.2.dist-info/METADATA
agtools-1.0.2.dist-info/RECORD
