Metadata-Version: 2.4
Name: agtools
Version: 1.0.2
Summary: agtools: A Software Framework to Manipulate Assembly Graphs
Keywords: metagenomics,assembly,graphs,bioinformatics
Author-email: Vijini Mallawaarachchi <viji.mallawaarachchi@gmail.com>
Requires-Python: >=3.9
License-File: LICENSE
Requires-Dist: click
Requires-Dist: loguru
Requires-Dist: bidict
Requires-Dist: biopython
Requires-Dist: igraph
Requires-Dist: pycairo
Requires-Dist: pandas
Requires-Dist: black ; extra == "dev"
Requires-Dist: click ; extra == "dev"
Requires-Dist: flit ; extra == "dev"
Requires-Dist: isort==5.13.2 ; extra == "dev"
Requires-Dist: agtools[test] ; extra == "dev"
Requires-Dist: pytest ; extra == "test"
Requires-Dist: pytest-cov ; extra == "test"
Requires-Dist: pytest-xdist ; extra == "test"
Project-URL: Home, https://agtools.readthedocs.io
Provides-Extra: dev
Provides-Extra: test
